setup.py
nose_profile/__init__.py
nose_profile/kcachegrind.py
nose_profile.egg-info/PKG-INFO
nose_profile.egg-info/SOURCES.txt
nose_profile.egg-info/dependency_links.txt
nose_profile.egg-info/entry_points.txt
nose_profile.egg-info/requires.txt
nose_profile.egg-info/top_level.txt