Metadata-Version: 1.0
Name: nose-profile
Version: 1.0
Summary: Calltree coverage plugin for nose
Home-page: https://github.com/sio2project/nose-profile
Author: The SIO2 Project Team
Author-email: sio2@sio2project.mimuw.edu.pl
License: GPL
Platform: UNKNOWN
